main.v
module shiftreg(input wire clk, load, cin, input wire[3:0] load_sig, output wire cout, output wire[3:0] out_sig);
    reg[3:0] r;
    assign cout = ~r[0];

    always @(posedge clk)
    begin
        if (load == 1) begin
            r[0] <= load_sig[0];
            r[1] <= load_sig[1];
            r[2] <= load_sig[2];
            r[3] <= load_sig[3];
        end else begin
            r[0] <= r[1];
            r[1] <= r[2];
            r[2] <= r[3];
            r[3] <= cin;
        end
    end

    assign out_sig = r;
endmodule

module halfadder(input wire a, b, output wire s, c);
    assign s = a ^ b;
    assign c = a & b;
endmodule

module addunit(input wire clk, cout, set, output wire nbit);
    wire t1, t2;
    reg carry;
    
    always @(posedge clk)
    begin
        if (set == 1) begin
            carry <= 1'b1;
        end else begin
            carry <= t2;
        end
    end

    halfadder hai1 (cout, carry, t1, t2);
    assign nbit = t1;
endmodule

module connect(input wire clk, load, input wire[3:0] load_sig, output wire[3:0] out_sig);
    wire t1, t2;
    shiftreg sri0 (clk, load, t1, load_sig, t2, out_sig);
    addunit aui0 (clk, t2, load, t1);
endmodule

module serialcompliment(input wire clk, set, input wire[3:0] load_sig, output wire[3:0] out_sig);
    wire t1, t2;

    assign t1 = 1'b1;
    assign t2 = 1'b0;

    connect ci0 (clk, set, load_sig, out_sig);
endmodule

tb.v
`timescale 1 ns / 100 ps

module tb;
    reg clk,set;
    wire [3:0] sig_in, sig_out;
    initial begin $dumpfile("htw.vcd"); $dumpvars(0,tb); end
    initial clk = 1'b0; always #5 clk =~ clk;
    initial set = 1'b1; always #10 set = 1'b0;
    assign sig_in[0] = 1'b0;
    assign sig_in[1] = 1'b1;
    assign sig_in[2] = 1'b0;
    assign sig_in[3] = 1'b1;

    serialcompliment sci0 (clk, set, sig_in, sig_out);

    initial begin
        #55 $finish;
    end
endmodule

htw.vcd
$date
	Tue Nov 19 00:04:22 2019
$end
$version
	Icarus Verilog
$end
$timescale
	100ps
$end
$scope module tb $end
$var wire 4 ! sig_out [3:0] $end
$var wire 4 " sig_in [3:0] $end
$var reg 1 # clk $end
$var reg 1 $ set $end
$scope module sci0 $end
$var wire 1 # clk $end
$var wire 4 % load_sig [3:0] $end
$var wire 1 $ set $end
$var wire 1 & t1 $end
$var wire 1 ' t2 $end
$var wire 4 ( out_sig [3:0] $end
$scope module ci0 $end
$var wire 1 # clk $end
$var wire 1 $ load $end
$var wire 4 ) load_sig [3:0] $end
$var wire 1 * t2 $end
$var wire 1 + t1 $end
$var wire 4 , out_sig [3:0] $end
$scope module aui0 $end
$var wire 1 # clk $end
$var wire 1 + nbit $end
$var wire 1 $ set $end
$var wire 1 - t2 $end
$var wire 1 . t1 $end
$var wire 1 * cout $end
$var reg 1 / carry $end
$scope module hai1 $end
$var wire 1 / b $end
$var wire 1 - c $end
$var wire 1 . s $end
$var wire 1 * a $end
$upscope $end
$upscope $end
$scope module sri0 $end
$var wire 1 + cin $end
$var wire 1 # clk $end
$var wire 1 * cout $end
$var wire 1 $ load $end
$var wire 4 0 load_sig [3:0] $end
$var wire 4 1 out_sig [3:0] $end
$var reg 4 2 r [3:0] $end
$upscope $end
$upscope $end
$upscope $end
$upscope $end
$enddefinitions $end
#0
$dumpvars
bx 2
bx 1
b1010 0
x/
x.
x-
bx ,
x+
x*
b1010 )
bx (
0'
1&
b1010 %
1$
0#
b1010 "
bx !
$end
#50
1-
0+
0.
1*
b1010 !
b1010 (
b1010 ,
b1010 1
b1010 2
1/
1#
#100
0#
0$
#150
0-
1+
1.
0*
b101 !
b101 (
b101 ,
b101 1
b101 2
1#
#200
0#
#250
1*
1+
1.
b1010 !
b1010 (
b1010 ,
b1010 1
b1010 2
0/
1#
#300
0#
#350
0+
0.
0*
b1101 !
b1101 (
b1101 ,
b1101 1
b1101 2
1#
#400
0#
#450
1+
1.
1*
b110 !
b110 (
b110 ,
b110 1
b110 2
1#
#500
0#
#550
0+
0.
0*
b1011 !
b1011 (
b1011 ,
b1011 1
b1011 2
1#
